Workbook

Sheet Resultado
A1: SIVEC · quanto entra, quanto custa e quanto sobra por mês
A2: Quatro cenários lado a lado. Tudo vem das outras abas; mude lá.
A4: Linha | B4: Red Centro (só o exemplo) | C4: Município · equipe enxuta | D4: Município · equipe completa | E4: Município + províncias
A5: Estabelecimentos cobrados | B5: =Estabelecimentos!D12 | C5: =Estabelecimentos!E12 | D5: =Estabelecimentos!E12 | E5: =Estabelecimentos!F12
A6: Mensalidades (US$/mês) | B6: =Estabelecimentos!D13 | C6: =Estabelecimentos!E13 | D6: =Estabelecimentos!E13 | E6: =Estabelecimentos!F13
A7: Faturamento (Bs/mês) | B7: =B6*Supostos!$B$12 | C7: =C6*Supostos!$B$12 | D7: =D6*Supostos!$B$12 | E7: =E6*Supostos!$B$12
A8: (−) Impostos sobre o faturamento | B8: =-B7*Supostos!$B$13 | C8: =-C7*Supostos!$B$13 | D8: =-D7*Supostos!$B$13 | E8: =-E7*Supostos!$B$13
A9: Receita líquida | B9: =B7+B8 | C9: =C7+C8 | D9: =D7+D8 | E9: =E7+E8
A10: (−) Equipe (salários + encargos + externos) | B10: =-Equipe!I13 | C10: =-Equipe!J13 | D10: =-Equipe!K13 | E10: =-Equipe!L13
A11: (−) Gastos fixos (aluguel, transporte, ferramentas…) | B11: =-Gastos!B13 | C11: =-Gastos!C13 | D11: =-Gastos!D13 | E11: =-Gastos!E13
A12: Resultado antes do IUE | B12: =B9+B10+B11 | C12: =C9+C10+C11 | D12: =D9+D10+D11 | E12: =E9+E10+E11
A13: (−) IUE | B13: =-MAX(0,B12)*Supostos!$B$14 | C13: =-MAX(0,C12)*Supostos!$B$14 | D13: =-MAX(0,D12)*Supostos!$B$14 | E13: =-MAX(0,E12)*Supostos!$B$14
A14: LUCRO LÍQUIDO DA EMPRESA (Bs/mês) | B14: =B12+B13 | C14: =C12+C13 | D14: =D12+D13 | E14: =E12+E13
A15: Lucro líquido (US$/mês) | B15: =B14/Supostos!$B$12 | C15: =C14/Supostos!$B$12 | D15: =D14/Supostos!$B$12 | E15: =E14/Supostos!$B$12
A16: Margem líquida | B16: =IFERROR(B14/B7,0) | C16: =IFERROR(C14/C7,0) | D16: =IFERROR(D14/D7,0) | E16: =IFERROR(E14/E7,0)
A17: Seu salário de diretor (Bs/mês) | B17: =Equipe!$C$5*Equipe!E5 | C17: =Equipe!$C$5*Equipe!F5 | D17: =Equipe!$C$5*Equipe!G5 | E17: =Equipe!$C$5*Equipe!H5
A18: Você recebe no total (salário + lucro, Bs/mês) | B18: =B17+B14 | C18: =C17+C14 | D18: =D17+D14 | E18: =E17+E14
A19: Pessoas contratadas | B19: =Equipe!E14 | C19: =Equipe!F14 | D19: =Equipe!G14 | E19: =Equipe!H14
A20: Lucro líquido por ano (Bs) | B20: =B14*12 | C20: =C14*12 | D20: =D14*12 | E20: =E14*12
A21: Implantação (US$, uma vez) | B21: =Estabelecimentos!D14 | C21: =Estabelecimentos!E14 | D21: =Estabelecimentos!E14 | E21: =Estabelecimentos!F14
A22: Implantação líquida de impostos (Bs) | B22: =B21*Supostos!$B$12*(1-Supostos!$B$13) | C22: =C21*Supostos!$B$12*(1-Supostos!$B$13) | D22: =D21*Supostos!$B$12*(1-Supostos!$B$13) | E22: =E21*Supostos!$B$12*(1-Supostos!$B$13)
A23: Caixa necessário antes de começar (Bs) | B23: =(-B10-B11)*Supostos!$B$16 | C23: =(-C10-C11)*Supostos!$B$16 | D23: =(-D10-D11)*Supostos!$B$16 | E23: =(-E10-E11)*Supostos!$B$16
A26: Como ler
A27: • Red Centro: renda extra enquanto você segue como médico; ainda não paga equipe nem escritório. Serve de vitrine.
A28: • Município · equipe enxuta: a recomendação para começar (4 pessoas + contador e advogado externos).
A29: • Município · equipe completa: 5 pessoas; o lucro cai muito. Só vale quando entrarem as províncias.
A30: • Município + províncias: +100 centros e +10 hospitais de 2º nível (estimativa); +1 mesa de ajuda e +1 implantador.
A31: • Os salários e gastos são estimativas de mercado: confirme com o contador antes de assinar.
A32: • "Caixa necessário": o Estado costuma pagar com 60–90 dias de atraso; é o dinheiro que precisa existir antes.

Sheet Supostos
A1: SIVEC · Supostos (mude aqui; o resto recalcula)
A2: Azul = você pode mudar. Amarelo = estimativa a confirmar. Preços definidos pelo autor em 27/09/2026.
A4: Suposto | B4: Valor | C4: Observação
A5: Mensalidade · 1º nível sem colposcopia (US$) | B5: 100 | C5: Definido pelo autor.
A6: Mensalidade · 1º nível com colposcopia e biópsia (US$) | B6: 250 | C6: Definido pelo autor.
A7: Mensalidade · hospital de 2º nível (US$) | B7: 250 | C7: Definido pelo autor.
A8: Mensalidade · 3º e 4º nível e laboratórios de PAP/VPH (US$) | B8: 501 | C8: Definido pelo autor.
A9: Implantação única · 1º nível (US$) | B9: 200 | C9: Definido pelo autor (vale para 1º nível com ou sem colposcopia).
A10: Implantação única · 2º nível (US$) | B10: 500 | C10: Definido pelo autor.
A11: Implantação única · 3º e 4º nível e laboratórios (US$) | B11: 550 | C11: Definido pelo autor.
A12: Câmbio (Bs por US$) | B12: 6.96 | C12: Câmbio oficial.
A13: Impostos sobre o faturamento (IVA 13% + IT 3%) | B13: 0.16 | C13: Bolívia. Supõe que o preço da tabela é o valor total da fatura (impostos dentro). Se o Estado pagar o preço + impostos, ponha 0.
A14: Imposto sobre o lucro (IUE) | B14: 0.25 | C14: Bolívia.
A15: Encargos sociais sobre salário | B15: 0.33 | C15: CNS 10% + AFP patronal ~6,7% + aguinaldo 8,33% + previsão de indenização 8,33%. Confirmar com o contador.
A16: Meses que o Estado demora para pagar | B16: 3 | C16: Pagamento público costuma atrasar 60–90 dias: é o caixa que você precisa ter antes.
... A18: Implantação única · tablero da rede (US$) | B18: 250 | C18: Como está no slide de preços.

Sheet Estabelecimentos
A1: Estabelecimentos cobrados em cada cenário
A2: Quantidades em azul; amarelo = estimativa (confirmar com a Secretaria Municipal de Saúde e o SEDES).
A4: Tipo de estabelecimento | B4: Mensalidade (US$) | C4: Implantação (US$) | D4: Qtd · Red Centro | E4: Qtd · Município | F4: Qtd · Município + províncias | G4: De onde vem a quantidade
A5: 1º nível sem colposcopia | B5: =Supostos!$B$5 | C5: =Supostos!$B$9 | D5: 8 | E5: 60 | F5: 160 | G5: Red Centro: 9 centros cadastrados no SIVEC, 1 deles com colposcopia. Município: 65 centros (El Deber) menos os que têm colposcopia. Províncias: +100 centros (estimativa).
A6: 1º nível com colposcopia e biópsia | B6: =Supostos!$B$6 | C6: =Supostos!$B$9 | D6: 1 | E6: 5 | F6: 5 | G6: Estimativa: ~1 por rede. Confirmar quais centros fazem colposcopia.
A7: Hospital de 2º nível | B7: =Supostos!$B$7 | C7: =Supostos!$B$10 | D7: 1 | E7: 5 | F7: 15 | G7: Município: 5 hospitais municipais (GAM). Províncias: +10 hospitais de 2º nível (estimativa).
A8: Hospital de 3º nível | B8: =Supostos!$B$8 | C8: =Supostos!$B$11 | D8: 0 | E8: 5 | F8: 5 | G8: Defensoría del Pueblo: 5 hospitais de 3º nível na cidade (confirmar o 5º).
A9: 4º nível · Instituto Oncológico | B9: =Supostos!$B$8 | C9: =Supostos!$B$11 | D9: 1 | E9: 1 | F9: 1 | G9: Já conectado ao SIVEC (laboratório e colposcopia).
A10: Laboratório de citologia independente | B10: =Supostos!$B$8 | C10: =Supostos!$B$11 | D10: 0 | E10: 0 | F10: 0 | G10: Se algum laboratório fora dos hospitais ler PAP/VPH, coloque aqui.
A11: Tablero da rede (gestor + mapa) | B11: =Supostos!$B$17 | C11: =Supostos!$B$18 | D11: 0 | E11: 0 | F11: 0 | G11: Em 0 = incluído no pacote (como no exemplo da apresentação). Ponha 1 por rede se for cobrar os US$ 250 do slide de preços (Município: 4 redes).
A12: TOTAL de estabelecimentos | D12: =SUM(D5:D11) | E12: =SUM(E5:E11) | F12: =SUM(F5:F11)
A13: Mensalidades (US$/mês) | D13: =SUMPRODUCT($B$5:$B$11,D5:D11) | E13: =SUMPRODUCT($B$5:$B$11,E5:E11) | F13: =SUMPRODUCT($B$5:$B$11,F5:F11)
A14: Implantação total (US$, uma vez) | D14: =SUMPRODUCT($C$5:$C$11,D5:D11) | E14: =SUMPRODUCT($C$5:$C$11,E5:E11) | F14: =SUMPRODUCT($C$5:$C$11,F5:F11)
A17: Lista de referência · município de Santa Cruz de la Sierra
A18: 4 redes municipais | B18: Red Centro, Red Norte, Red Sur, Red Este (GAM Santa Cruz). Tablero da rede: ver a linha "Tablero da rede" acima.
A19: Red Centro · 9 centros | B19: Elvira Wunderlich, Perpetuo Socorro, Roque Aguilera, San Carlos, San Luis, Santa Rosita, Virgen de Cotoca, Virgen de Fátima, Willy Lemaitre.
A20: Hospitais municipais de 2º nível | B20: Francés, Villa 1ro de Mayo, Pampa de la Isla, Plan 3000, Bajío del Oriente.
A21: Hospitais de 3º nível | B21: San Juan de Dios, Japonés, de Niños Dr. Mario Ortiz Suárez, de la Mujer Dr. Percy Boland, 5º a confirmar.
A22: 4º nível | B22: Instituto Oncológico del Oriente Boliviano.

Sheet Equipe
A1: Equipe por cenário
A2: Salário mensal em Bs (estimativa de mercado em Santa Cruz). Pessoas em azul: mude à vontade. Externos não pagam encargos.
A4: Cargo | B4: O que faz | C4: Salário (Bs/mês) | D4: Externo? (1=sim) | E4: Pessoas · Red Centro (só o exemplo) | F4: Pessoas · Município · equipe enxuta | G4: Pessoas · Município · equipe completa | H4: Pessoas · Município + províncias | I4: Custo · Red Centro (só o exemplo) | J4: Custo · Município · equipe enxuta | K4: Custo · Município · equipe completa | L4: Custo · Município + províncias
A5: Fundador / diretor | B5: Você: produto, parte clínica, contratos com o município e o SEDES. Na Red Centro você segue como médico e não tira salário. | C5: 10000 | D5: 0 | E5: 0 | F5: 1 | G5: 1 | H5: 1 | I5: =$C5*E5*(1+IF($D5=1,0,Supostos!$B$15)) | J5: =$C5*F5*(1+IF($D5=1,0,Supostos!$B$15)) | K5: =$C5*G5*(1+IF($D5=1,0,Supostos!$B$15)) | L5: =$C5*H5*(1+IF($D5=1,0,Supostos!$B$15))
A6: Desenvolvedor full-stack | B6: Correções, melhorias, relatórios novos; responde pelo sistema perante o município. | C6: 8500 | D6: 0 | E6: 0 | F6: 1 | G6: 1 | H6: 1 | I6: =$C6*E6*(1+IF($D6=1,0,Supostos!$B$15)) | J6: =$C6*F6*(1+IF($D6=1,0,Supostos!$B$15)) | K6: =$C6*G6*(1+IF($D6=1,0,Supostos!$B$15)) | L6: =$C6*H6*(1+IF($D6=1,0,Supostos!$B$15))
A7: Suporte + capacitação | B7: Enfermeira ou licenciada: atende por telefone/WhatsApp, cria usuários e vai aos centros capacitar. | C7: 5500 | D7: 0 | E7: 0 | F7: 1 | G7: 0 | H7: 1 | I7: =$C7*E7*(1+IF($D7=1,0,Supostos!$B$15)) | J7: =$C7*F7*(1+IF($D7=1,0,Supostos!$B$15)) | K7: =$C7*G7*(1+IF($D7=1,0,Supostos!$B$15)) | L7: =$C7*H7*(1+IF($D7=1,0,Supostos!$B$15))
A8: Mesa de ajuda | B8: Só atendimento remoto (telefone, WhatsApp, e-mail). | C8: 4000 | D8: 0 | E8: 0 | F8: 0 | G8: 1 | H8: 1 | I8: =$C8*E8*(1+IF($D8=1,0,Supostos!$B$15)) | J8: =$C8*F8*(1+IF($D8=1,0,Supostos!$B$15)) | K8: =$C8*G8*(1+IF($D8=1,0,Supostos!$B$15)) | L8: =$C8*H8*(1+IF($D8=1,0,Supostos!$B$15))
A9: Implantador / capacitador | B9: Vai a cada centro e hospital; 1 pessoa dá conta de ~40 centros por semestre de implantação. | C9: 6000 | D9: 0 | E9: 0 | F9: 0 | G9: 1 | H9: 1 | I9: =$C9*E9*(1+IF($D9=1,0,Supostos!$B$15)) | J9: =$C9*F9*(1+IF($D9=1,0,Supostos!$B$15)) | K9: =$C9*G9*(1+IF($D9=1,0,Supostos!$B$15)) | L9: =$C9*H9*(1+IF($D9=1,0,Supostos!$B$15))
A10: Administrativo e financeiro (meio período) | B10: Faturas ao município, cobranças, pagamentos. | C10: 2500 | D10: 0 | E10: 0 | F10: 1 | G10: 1 | H10: 1 | I10: =$C10*E10*(1+IF($D10=1,0,Supostos!$B$15)) | J10: =$C10*F10*(1+IF($D10=1,0,Supostos!$B$15)) | K10: =$C10*G10*(1+IF($D10=1,0,Supostos!$B$15)) | L10: =$C10*H10*(1+IF($D10=1,0,Supostos!$B$15))
A11: Contador (externo) | B11: Impostos, balanços, folha de pagamento. | C11: 1500 | D11: 1 | E11: 1 | F11: 1 | G11: 1 | H11: 1 | I11: =$C11*E11*(1+IF($D11=1,0,Supostos!$B$15)) | J11: =$C11*F11*(1+IF($D11=1,0,Supostos!$B$15)) | K11: =$C11*G11*(1+IF($D11=1,0,Supostos!$B$15)) | L11: =$C11*H11*(1+IF($D11=1,0,Supostos!$B$15))
A12: Advogado (externo, por demanda) | B12: Contratos, SENAPI, proteção de dados. | C12: 1000 | D12: 1 | E12: 0 | F12: 1 | G12: 1 | H12: 1 | I12: =$C12*E12*(1+IF($D12=1,0,Supostos!$B$15)) | J12: =$C12*F12*(1+IF($D12=1,0,Supostos!$B$15)) | K12: =$C12*G12*(1+IF($D12=1,0,Supostos!$B$15)) | L12: =$C12*H12*(1+IF($D12=1,0,Supostos!$B$15))
A13: TOTAL | E13: =SUM(E5:E12) | F13: =SUM(F5:F12) | G13: =SUM(G5:G12) | H13: =SUM(H5:H12) | I13: =SUM(I5:I12) | J13: =SUM(J5:J12) | K13: =SUM(K5:K12) | L13: =SUM(L5:L12)
A14: Só pessoas contratadas (sem externos) | E14: =SUMPRODUCT(E5:E12,1-$D$5:$D$12) | F14: =SUMPRODUCT(F5:F12,1-$D$5:$D$12) | G14: =SUMPRODUCT(G5:G12,1-$D$5:$D$12) | H14: =SUMPRODUCT(H5:H12,1-$D$5:$D$12)
A15: Custo mensal em US$ | I15: =I13/Supostos!$B$12 | J15: =J13/Supostos!$B$12 | K15: =K13/Supostos!$B$12 | L15: =L13/Supostos!$B$12
A17: Implantação (primeiros 6 meses): contrate implantadores temporários pagos com a taxa de implantação (ver Resultado, linha "Implantação líquida").

Sheet Gastos
A1: Gastos fixos por mês (Bs)
A2: Aluguel, transporte, ferramentas e o resto. Valores em azul; mude pelo que você cotar.
A4: Gasto | B4: Red Centro (só o exemplo) | C4: Município · equipe enxuta | D4: Município · equipe completa | E4: Município + províncias | F4: Observação
A5: Aluguel de sala (30–40 m²) | B5: 0 | C5: 2100 | D5: 2800 | E5: 2800 | F5: Sala pequena entre o 2º e o 4º anel. Na Red Centro você trabalha de casa.
A6: Luz, internet e condomínio | B6: 0 | C6: 600 | D6: 700 | E6: 700
A7: Transporte na cidade | B7: 500 | C7: 1200 | D7: 1500 | E7: 1500 | F7: Táxi/combustível para capacitação e visitas aos centros.
A8: Viagens às províncias (passagem + diárias) | B8: 0 | C8: 0 | D8: 0 | E8: 4000 | F8: ~4 viagens/mês de Bs 1.000 (passagem, hospedagem, alimentação).
A9: Notebooks e celulares (divididos em 36 meses) | B9: 0 | C9: 700 | D9: 1000 | E9: 1000
A10: Reserva para imprevistos | B10: 0 | C10: 2000 | D10: 2000 | E10: 3500 | F10: Equipamento que quebra, multa, viagem urgente.
A11: Ferramentas e nuvem (US$/mês) | B11: 150 | C11: 360 | D11: 430 | E11: 500 | F11: Supabase Pro + computação, hospedagem, domínio, e-mail, backups, monitoramento, contas da equipe. Detalhe na aba Ferramentas.
A12: Ferramentas e nuvem (Bs/mês) | B12: =B11*Supostos!$B$12 | C12: =C11*Supostos!$B$12 | D12: =D11*Supostos!$B$12 | E12: =E11*Supostos!$B$12
A13: TOTAL gastos fixos (Bs/mês) | B13: =SUM(B5:B10)+B12 | C13: =SUM(C5:C10)+C12 | D13: =SUM(D5:D10)+D12 | E13: =SUM(E5:E10)+E12

Sheet Ferramentas
A1: Ferramentas para manter o SIVEC (referência para a aba Gastos)
A2: US$ por mês, cenário Município. WhatsApp Business é opcional: só se for avisar as pacientes por WhatsApp.
A4: Ferramenta | B4: Para que serve | C4: Fornecedor sugerido | D4: US$/mês
A5: Banco de dados, login e backups | B5: Todos os dados, login e cópias diárias. | C5: Supabase Pro + computação | D5: 135
A6: Hospedagem do aplicativo | B6: Sistema publicado com endereço próprio. | C6: Vercel / Cloudflare | D6: 20
A7: Domínio e certificado | B7: sivec.bo com HTTPS. | C7: NIC Bolivia + Cloudflare | D7: 3
A8: E-mail transacional | B8: Senhas e avisos por e-mail. | C8: Resend / SendGrid | D8: 20
A9: Monitoramento de erros | B9: Avisa quando algo falha num centro. | C9: Sentry | D9: 26
A10: Monitor de disponibilidade | B10: Alerta se o sistema cair. | C10: Better Stack / UptimeRobot | D10: 25
A11: Backup externo | B11: Segunda cópia fora do Supabase. | C11: Backblaze B2 | D11: 20
A12: Contas da equipe (e-mail, código, senhas) | B12: ~US$ 15 por pessoa. | C12: Google Workspace, GitHub, Bitwarden | D12: 90
A13: WhatsApp Business API (opcional) | B13: Avisos às pacientes. | C13: 360dialog / Twilio | D13: 0
A14: TOTAL (US$/mês) | D14: =SUM(D5:D13)
A16: Auditoria de segurança anual (~US$ 3.000–8.000) e seguro de responsabilidade: pagar com a reserva quando o contrato exigir.

Sheet Papel vs SIVEC
A1: Papel vs SIVEC · quanto o sistema devolve em tempo e insumos (cenário Município)
A2: Não há dado público de quanto o SUS gasta com papel no PAP: é uma estimativa de baixo para cima. Azul = mude.
A4: Suposto / cálculo | B4: Valor | C4: Observação e fonte
A5: Centros de 1º nível no município | B5: =Estabelecimentos!E5+Estabelecimentos!E6 | C5: Aba Estabelecimentos.
A6: Tomas de PAP/VPH por centro por ano | B6: 300 | C6: San Luis registrou 529 em 12 meses no SIVEC; centros menores fazem menos. Estimativa.
A7: Tomas por ano no município | B7: =B5*B6
A8: Folhas de papel por toma | B8: 3.5 | C8: Ficha de solicitação (com cópia), informe de resultado, lista de lote, registro no livro, referência e contrarreferência das positivas. Estimativa.
A9: Custo por folha (papel + impressão/fotocópia, Bs) | B9: 0.25 | C9: Estimativa.
A10: Papel por ano (Bs) | B10: =B7*B8*B9
A11: Minutos de papelada economizados por toma | B11: 15 | C11: Copiar dados no livro, montar a lista do lote, procurar o resultado, passar ao SNIS. Estudo em 5 países: registrar leva ~1/3 do tempo da consulta (BMC Health Serv Res 2021).
A12: Horas por mês de informes do PAP por centro (SNIS, listas) | B12: 2 | C12: Mesmo estudo: ~9 h/mês de informes por trabalhador (todos os programas); aqui só a parte do PAP.
A13: Custo de uma hora de enfermeira/licenciada (Bs) | B13: =6000/176*(1+Supostos!$B$15) | C13: Salário de Bs 6.000 ÷ 176 h + encargos.
A14: Horas devolvidas por ano | B14: =B7*B11/60+B5*B12*12
A15: Equivale a enfermeiras em tempo integral | B15: =B14/(176*12) | C15: Tempo que volta para atender pacientes.
A16: Valor do tempo devolvido (Bs/ano) | B16: =B14*B13
A17: % de tomas repetidas por resultado ou lâmina perdidos (sem SIVEC) | B17: 0.03 | C17: Estimativa. Antes do SIVEC, San Luis entregava 15 de 402 resultados.
A18: Custo de repetir uma toma (Bs) | B18: 60 | C18: Insumos + leitura no laboratório + hora da profissional. Estimativa.
A19: Tomas repetidas evitadas (Bs/ano) | B19: =B7*B17*B18
A20: ECONOMIA TOTAL POR ANO (Bs) | B20: =B10+B16+B19
A21: Economia total por ano (US$) | B21: =B20/Supostos!$B$12
A22: Custo anual do SIVEC no município (US$) | B22: =Estabelecimentos!E13*12 | C22: Mensalidades × 12.
A23: O papel e o tempo pagam esta parte do SIVEC | B23: =IFERROR(B21/B22,0) | C23: O resto se paga com os tratamentos de câncer evitados (aba Vidas e impacto).

Sheet Vidas e impacto
A1: Vidas e impacto · o que o SIVEC muda para as mulheres (cenário Município, por ano)
A2: Modelo conservador: conta só as lesões de alto grau que, sem o SIVEC, se perderiam no caminho e agora são tratadas.
A4: Suposto / cálculo | B4: Valor | C4: Observação e fonte
A5: Tomas por ano no município | B5: ='Papel vs SIVEC'!B7 | C5: Aba Papel vs SIVEC.
A6: % com lesão de alto grau ou mais (HSIL, ASC-H, AGC, carcinoma) | B6: 0.015 | C6: Estimativa para a população tamizada em Santa Cruz; confirmar com o Oncológico.
A7: Lesões de alto grau detectadas por ano | B7: =B5*B6
A8: % que completa o tratamento SEM SIVEC | B8: 0.3 | C8: Estimativa conservadora. Em San Luis, antes do SIVEC, só 15 de 402 resultados chegavam à paciente.
A9: % que completa o tratamento COM SIVEC | B9: 0.7 | C9: Meta. Em San Luis, com o SIVEC: 73% dos resultados entregues e as positivas sem conduta identificadas pelo nome.
A10: Mulheres a mais tratadas a tempo, por ano | B10: =B7*(B9-B8)
A11: % de lesões de alto grau não tratadas que viram câncer | B11: 0.2 | C11: Conservador. NIC 3 sem tratamento: ~31% viram câncer invasor em 30 anos (McCredie, Lancet Oncol 2008).
A12: Cânceres evitados por ano | B12: =B10*B11
A13: % das mulheres com câncer que morrem (Bolívia) | B13: =18.3/38.7 | C13: Mortalidade 18,3 ÷ incidência 38,7 por 100 mil (GLOBOCAN 2022, a mais alta da América do Sul).
A14: VIDAS SALVAS POR ANO | B14: =B12*B13
A15: Filhos por mãe que morre de câncer de colo | B15: 2.1 | C15: Em países de renda média-baixa, cada 100 mães mortas deixam ~210 órfãos (Guida et al., Nature Medicine 2022).
A16: CRIANÇAS QUE NÃO FICAM ÓRFÃS POR ANO | B16: =B14*B15
A17: Anos de vida perdidos por cada morte | B17: 20 | C17: Morre-se em média entre 45 e 55 anos; expectativa de vida das mulheres na Bolívia ~70.
A18: Anos de vida salvos por ano | B18: =B14*B17
A19: Renda nacional por habitante (US$/ano) | B19: 3690 | C19: Banco Mundial, RNB per capita (Atlas) 2024.
A20: Valor produtivo das vidas salvas (US$/ano) | B20: =B18*B19 | C20: Só o que essas mulheres produziriam; não inclui o valor para a família.
A21: Valor estatístico de uma vida na Bolívia (US$) | B21: 127000 | C21: Caso de referência para países de renda média-baixa (Robinson, Hammitt e O'Keeffe, J Benefit-Cost Anal 2019): extrapolado dos EUA com elasticidade 1,5; piso de 20 × a renda por habitante (≈ US$ 74 mil).
A22: Valor estatístico das vidas salvas (US$/ano) | B22: =B14*B21
A23: Custo para o SUS de tratar um câncer de colo (Bs) | B23: 60000 | C23: Radioterapia externa Bs 20–30 mil + braquiterapia Bs 13–25 mil + quimioterapia ~Bs 6 mil/mês (Ministerio de Salud).
A24: Custo de tratar uma lesão de alto grau a tempo (Bs) | B24: 800 | C24: Colposcopia + biópsia + LEEP/crioterapia. Estimativa.
A25: Tratamentos de câncer evitados (Bs/ano) | B25: =B12*B23-B10*B24 | C25: Já desconta o custo de tratar as lesões a tempo.
A26: Tratamentos de câncer evitados (US$/ano) | B26: =B25/Supostos!$B$12
A27: Custo anual do SIVEC no município (US$) | B27: ='Papel vs SIVEC'!B22
A28: Cada US$ 1 do SIVEC devolve ao SUS em tratamentos (US$) | B28: =IFERROR(B26/B27,0) | C28: Só tratamentos; sem contar o valor das vidas.
A29: Cada US$ 1 do SIVEC devolve, contando tudo (US$) | B29: =IFERROR((B26+'Papel vs SIVEC'!B21+B20)/B27,0) | C29: Tratamentos + papel e tempo + valor produtivo das vidas.
A30: Com teste de VPH em vez de PAP | B30: proteção 60–70% maior | C30: Contra o câncer invasor, em 4 ensaios europeus com 176 mil mulheres (Ronco et al., Lancet 2014). Os cânceres evitados subiriam na mesma direção.
A36: Os cânceres evitados aparecem ao longo de 5 a 15 anos: a lesão tratada hoje é o câncer que não chega amanhã. Números para sensibilizar, não uma promessa: confirmar os supostos com o Oncológico e o SEDES.

Sheet Fontes
A1: Fontes
A2: Consultadas em 27/09/2026.
A4: O que | B4: Link
A5: GLOBOCAN 2022 · América Latina | B5: https://aacrjournals.org/cancerrescommun/article/5/12/2236/771224/Cancer-Incidence-and-Mortality-Estimates-in-Latin
A6: Ministerio de Salud · 4 a 5 mulheres morrem por dia | B6: https://www.minsalud.gob.bo/8548-por-la-vida-de-las-mujeres-gobierno-fortalece-la-prevencion-y-atencion-del-cancer-cervico-uterino-con-servicios-gratuitos-en-todo-el-pais
A7: Ministerio de Salud · custo da radioterapia e quimioterapia | B7: https://www.minsalud.gob.bo/8626-cancer-el-sus-convirtio-los-tratamientos-de-quimioterapia-y-radioterapia-de-bs-50-000-a-gratuitas
A8: Defensoría del Pueblo · 35,5% dos casos em Santa Cruz | B8: https://www.defensoria.gob.bo/uploads/files/informe-cancer-cervico-uterino-y-de-mama.pdf
A9: OPS · Plano para acelerar a eliminação 2026–2030 | B9: https://www.paho.org/es/noticias/6-11-2025-futuro-sin-cancer-cuello-uterino-bolivia-presenta-su-plan-para-acelerar
A10: Ronco et al., Lancet 2014 · VPH vs citologia | B10: https://pubmed.ncbi.nlm.nih.gov/24192252/
A11: Guida et al., Nature Medicine 2022 · órfãos por câncer materno | B11: https://www.nature.com/articles/s41591-022-02109-2
A12: Robinson, Hammitt e O'Keeffe 2019 · valor da vida em países de renda média-baixa | B12: https://www.cambridge.org/core/journals/journal-of-benefit-cost-analysis/article/valuing-mortality-risk-reductions-in-global-benefitcost-analysis/71252D2A48B3F2402DF209550C1945FA
A13: BMC Health Services Research 2021 · tempo gasto em registros | B13: https://link.springer.com/article/10.1186/s12913-021-06652-5
A14: Banco Mundial · RNB per capita da Bolívia | B14: https://data.worldbank.org/indicator/NY.GNP.PCAP.CD?locations=BO
