Workbook

Sheet Supuestos
A1: SIVEC · Supuestos del modelo (celdas amarillas = editar)
A2: Valores de referencia para negociar; validar con proveedores y con el cliente. Precios SIN impuestos.
A3: Supuesto | B3: Valor | C3: Unidad | D3: Nota
A4: General
A5: Tipo de cambio Bs por US$ | B5: 6.96 | C5: Bs/US$ | D5: oficial; revisar
A6: Impuestos sobre la factura (IVA 13% + IT 3%) | B6: 0.16 | C6: % | D6: se suman al precio al facturar
A7: Impuesto a las utilidades (IUE) | B7: 0.25 | C7: %
A8: Días que tarda el Estado en pagar | B8: 90 | C8: días | D8: capital de trabajo necesario
A9: Precio mensual por establecimiento (licencia + soporte + nube)
A10: 1er nivel (puesto / centro de salud) | B10: 180 | C10: US$/mes | D10: ≈ Bs 1.250
A11: 2º nivel (hospital básico) | B11: 1400 | C11: US$/mes
A12: 3er nivel (hospital de especialidades) | B12: 3800 | C12: US$/mes
A13: Implementación única por establecimiento (instalación, datos, capacitación)
A14: 1er nivel | B14: 600 | C14: US$
A15: 2º nivel | B15: 6000 | C15: US$
A16: 3er nivel | B16: 15000 | C16: US$
A17: Kit de equipos por establecimiento (opcional, lo puede comprar el Estado)
A18: 1er nivel: lector de huella, tablet, celular, impresora, TV de turnos | B18: 900 | C18: US$
A19: 2º nivel: kits por servicio + carros de visita | B19: 9000 | C19: US$
A20: 3er nivel | B20: 20000 | C20: US$
A21: Costo variable por establecimiento por mes
A22: Nube / servidores — 1er nivel | B22: 8 | C22: US$/mes
A23: Nube / servidores — 2º nivel | B23: 60 | C23: US$/mes
A24: Nube / servidores — 3er nivel | B24: 150 | C24: US$/mes
A25: SMS — 1er nivel | B25: 10 | C25: US$/mes | D25: recordatorios, resultados
A26: SMS — 2º nivel | B26: 60 | C26: US$/mes
A27: SMS — 3er nivel | B27: 150 | C27: US$/mes
A28: Soporte técnico local: 1 técnico cada N establecimientos (1er nivel equiv.) | B28: 60 | C28: estab. | D28: 2º nivel = 8 equiv., 3er = 20
A29: Sueldo técnico de soporte | B29: 900 | C29: US$/mes
A30: Capacitador: 1 cada N establecimientos en implantación | B30: 40 | C30: estab.
A31: Sueldo capacitador | B31: 900 | C31: US$/mes
A32: Equipo central fijo (US$/mes)
A33: Desarrollo (4 programadores) | B33: 7200 | C33: US$/mes
A34: Calidad y pruebas (1) | B34: 1200 | C34: US$/mes
A35: Jefe de proyecto (1) | B35: 2000 | C35: US$/mes
A36: Dirección médica / producto | B36: 2500 | C36: US$/mes
A37: Seguridad, copias, dominio, herramientas | B37: 600 | C37: US$/mes
A38: Contabilidad y legal | B38: 800 | C38: US$/mes
A39: Comercial y relación con el gobierno | B39: 1500 | C39: US$/mes
A40: Total equipo central fijo | B40: =SUM(B33:B39) | C40: US$/mes

Sheet Escenarios
A1: SIVEC · Escenarios (número de establecimientos aproximado — validar con el RUES / SNIS)
A3: Concepto | B3: Piloto · Red Centro | C3: Municipio Santa Cruz de la Sierra | D3: Departamento de Santa Cruz | E3: Bolivia (nacional)
A4: Establecimientos 1er nivel | B4: 25 | C4: 110 | D4: 620 | E4: 3600
A5: Establecimientos 2º nivel | B5: 1 | C5: 10 | D5: 45 | E5: 220
A6: Establecimientos 3er nivel | B6: 0 | C6: 6 | D6: 12 | E6: 60
A7: Población cubierta (habitantes) | B7: 180000 | C7: 1700000 | D7: 3400000 | E7: 12200000
A9: Establecimientos equivalentes (1er=1, 2º=8, 3er=20) | B9: =B4+8*B5+20*B6 | C9: =C4+8*C5+20*C6 | D9: =D4+8*D5+20*D6 | E9: =E4+8*E5+20*E6
A10: INGRESO MENSUAL (US$, sin impuestos) | B10: =B4*Supuestos!$B$10+B5*Supuestos!$B$11+B6*Supuestos!$B$12 | C10: =C4*Supuestos!$B$10+C5*Supuestos!$B$11+C6*Supuestos!$B$12 | D10: =D4*Supuestos!$B$10+D5*Supuestos!$B$11+D6*Supuestos!$B$12 | E10: =E4*Supuestos!$B$10+E5*Supuestos!$B$11+E6*Supuestos!$B$12
A11: Ingreso mensual en Bs | B11: =B10*Supuestos!$B$5 | C11: =C10*Supuestos!$B$5 | D11: =D10*Supuestos!$B$5 | E11: =E10*Supuestos!$B$5
A12: Ingreso anual (US$) | B12: =B10*12 | C12: =C10*12 | D12: =D10*12 | E12: =E10*12
A13: Factura mensual al Estado con impuestos (US$) | B13: =B10*(1+Supuestos!$B$6) | C13: =C10*(1+Supuestos!$B$6) | D13: =D10*(1+Supuestos!$B$6) | E13: =E10*(1+Supuestos!$B$6)
A14: Costo variable nube + SMS (US$/mes) | B14: =B4*(Supuestos!$B$22+Supuestos!$B$25)+B5*(Supuestos!$B$23+Supuestos!$B$26)+B6*(Supuestos!$B$24+Supuestos!$B$27) | C14: =C4*(Supuestos!$B$22+Supuestos!$B$25)+C5*(Supuestos!$B$23+Supuestos!$B$26)+C6*(Supuestos!$B$24+Supuestos!$B$27) | D14: =D4*(Supuestos!$B$22+Supuestos!$B$25)+D5*(Supuestos!$B$23+Supuestos!$B$26)+D6*(Supuestos!$B$24+Supuestos!$B$27) | E14: =E4*(Supuestos!$B$22+Supuestos!$B$25)+E5*(Supuestos!$B$23+Supuestos!$B$26)+E6*(Supuestos!$B$24+Supuestos!$B$27)
A15: Soporte técnico local (US$/mes) | B15: =ROUNDUP(B9/Supuestos!$B$28,0)*Supuestos!$B$29 | C15: =ROUNDUP(C9/Supuestos!$B$28,0)*Supuestos!$B$29 | D15: =ROUNDUP(D9/Supuestos!$B$28,0)*Supuestos!$B$29 | E15: =ROUNDUP(E9/Supuestos!$B$28,0)*Supuestos!$B$29
A16: Equipo central fijo (US$/mes) | B16: =Supuestos!$B$40*IF(B9>300,2.5,IF(B9>100,1.5,1)) | C16: =Supuestos!$B$40*IF(C9>300,2.5,IF(C9>100,1.5,1)) | D16: =Supuestos!$B$40*IF(D9>300,2.5,IF(D9>100,1.5,1)) | E16: =Supuestos!$B$40*IF(E9>300,2.5,IF(E9>100,1.5,1))
A17: COSTO MENSUAL TOTAL (US$) | B17: =B14+B15+B16 | C17: =C14+C15+C16 | D17: =D14+D15+D16 | E17: =E14+E15+E16
A18: MARGEN MENSUAL ANTES DE IMPUESTOS (US$) | B18: =B10-B17 | C18: =C10-C17 | D18: =D10-D17 | E18: =E10-E17
A19: Margen % | B19: =IF(B10=0,0,B18/B10) | C19: =IF(C10=0,0,C18/C10) | D19: =IF(D10=0,0,D18/D10) | E19: =IF(E10=0,0,E18/E10)
A20: Utilidad neta mensual después de IUE (US$) | B20: =IF(B18>0,B18*(1-Supuestos!$B$7),B18) | C20: =IF(C18>0,C18*(1-Supuestos!$B$7),C18) | D20: =IF(D18>0,D18*(1-Supuestos!$B$7),D18) | E20: =IF(E18>0,E18*(1-Supuestos!$B$7),E18)
A21: Implementación única (US$) | B21: =B4*Supuestos!$B$14+B5*Supuestos!$B$15+B6*Supuestos!$B$20 | C21: =C4*Supuestos!$B$14+C5*Supuestos!$B$15+C6*Supuestos!$B$20 | D21: =D4*Supuestos!$B$14+D5*Supuestos!$B$15+D6*Supuestos!$B$20 | E21: =E4*Supuestos!$B$14+E5*Supuestos!$B$15+E6*Supuestos!$B$20
A22: Kit de equipos opcional (US$) | B22: =B4*Supuestos!$B$18+B5*Supuestos!$B$19+B6*Supuestos!$B$20 | C22: =C4*Supuestos!$B$18+C5*Supuestos!$B$19+C6*Supuestos!$B$20 | D22: =D4*Supuestos!$B$18+D5*Supuestos!$B$19+D6*Supuestos!$B$20 | E22: =E4*Supuestos!$B$18+E5*Supuestos!$B$19+E6*Supuestos!$B$20
A23: Capacitadores durante 6 meses de implantación (US$) | B23: =ROUNDUP((B4+B5+B6)/Supuestos!$B$30,0)*Supuestos!$B$31*6 | C23: =ROUNDUP((C4+C5+C6)/Supuestos!$B$30,0)*Supuestos!$B$31*6 | D23: =ROUNDUP((D4+D5+D6)/Supuestos!$B$30,0)*Supuestos!$B$31*6 | E23: =ROUNDUP((E4+E5+E6)/Supuestos!$B$30,0)*Supuestos!$B$31*6
A24: Capital de trabajo por atraso de pago (US$) | B24: =B17*Supuestos!$B$8/30 | C24: =C17*Supuestos!$B$8/30 | D24: =D17*Supuestos!$B$8/30 | E24: =E17*Supuestos!$B$8/30
A25: Costo por establecimiento equivalente (US$/mes) | B25: =IF(B9=0,0,B17/B9) | C25: =IF(C9=0,0,C17/C9) | D25: =IF(D9=0,0,D17/D9) | E25: =IF(E9=0,0,E17/E9)
A26: Costo para el Estado por habitante por año (US$) | B26: =IF(B7=0,0,B12/B7) | C26: =IF(C7=0,0,C12/C7) | D26: =IF(D7=0,0,D12/D7) | E26: =IF(E7=0,0,E12/E7)
A27: Costo por habitante por mes (Bs) | B27: =IF(B7=0,0,B10BS/B7) | C27: =IF(C7=0,0,C10BS/C7) | D27: =IF(D7=0,0,D10BS/D7) | E27: =IF(E7=0,0,E10BS/E7)
A29: Punto de equilibrio: establecimientos de 1er nivel necesarios para pagar el equipo central | B29: =ROUNDUP(Supuestos!$B$40/(Supuestos!$B$10-Supuestos!$B$22-Supuestos!$B$25-Supuestos!$B$29/Supuestos!$B$28),0)
A31: Alternativa: precio global por habitante
A32: Precio por habitante por año (US$) | B32: 1.2
A33: Contrato anual a precio global (US$) | B33: =B7*$B$32 | C33: =C7*$B$32 | D33: =D7*$B$32 | E33: =E7*$B$32
A35: Referencia: gasto total en salud de Bolivia ≈ US$ 3.000 millones/año (aprox., validar). SIVEC nacional como % de ese gasto: | E35: =E12/3000000000

Sheet Métricas
A1: SIVEC · Métricas para operar el negocio y demostrar el cambio
A3: Área | B3: Métrica | C3: Cómo se calcula | D3: Meta | E3: Frecuencia
A4: Financiera | B4: MRR (ingreso mensual recurrente) | C4: suma de licencias activas | D4: crece según fases | E4: mensual
A5: Financiera | B5: ARR (ingreso anual recurrente) | C5: MRR × 12 | D5: — | E5: mensual
A6: Financiera | B6: Margen bruto | C6: (ingreso − nube − SMS − soporte) / ingreso | D6: ≥ 70% | E6: mensual
A7: Financiera | B7: Margen operativo (EBITDA) | C7: ingreso − todos los costos operativos | D7: ≥ 25% desde el año 2 | E7: mensual
A8: Financiera | B8: Costo de servir por establecimiento | C8: costos variables + soporte / establecimientos | D8: < 35% del precio | E8: mensual
A9: Financiera | B9: Días de cobro (DSO) | C9: cuentas por cobrar / ingreso diario | D9: ≤ 90 días | E9: mensual
A10: Financiera | B10: Caja disponible en meses | C10: caja / costo mensual | D10: ≥ 4 meses | E10: mensual
A11: Financiera | B11: Renovación de contratos | C11: contratos renovados / contratos que vencen | D11: ≥ 90% | E11: anual
A12: Financiera | B12: Costo de adquisición por red (CAC) | C12: gasto comercial / redes nuevas | D12: recuperado en < 12 meses | E12: trimestral
A13: Operación | B13: Disponibilidad del sistema | C13: minutos en línea / minutos del mes | D13: ≥ 99,5% | E13: mensual
A14: Operación | B14: Tiempo de respuesta a incidentes críticos | C14: hora aviso → hora solución | D14: < 4 h | E14: semanal
... A29: Impacto (para el gobierno) | B29: Control prenatal ≥ 4 / ≥ 8 contactos | C29: embarazadas con controles / embarazadas | D29: ≥ 80% / ≥ 50% | E29: mensual

Sheet Datos para operar
A1: SIVEC · Qué se necesita para mantener el sistema funcionando
A3: Componente | B3: Qué es | C3: Opción recomendada | D3: Costo aproximado
A4: Servidores y base de datos | B4: donde viven los datos (PostgreSQL) | C4: nube con respaldo en Bolivia o servidor del Ministerio (AGETIC) | D4: ver hoja Escenarios
A5: Copias de seguridad | B5: copia diaria cifrada fuera del servidor | C5: copia automática + restauración de prueba semanal | D5: incluido en nube
A6: Dominio y certificados | B6: sivec.bo, conexión segura | C6: ADSIB para .bo | D6: < US$ 100/año
A7: SMS | B7: recordatorios y resultados | C7: convenio con operadora (Entel/Tigo/Viva) por volumen | D7: US$ 0,01–0,03 por SMS
A8: Firma digital | B8: firma legal de documentos | C8: ADSIB (firma digital del Estado) | D8: según convenio
A9: Integraciones | B9: SEGIP, SNIS, SUS, laboratorios | C9: convenios interinstitucionales | D9: sin costo de licencia
A10: Equipo humano | B10: desarrollo, soporte, capacitación | C10: ver hoja Supuestos | D10: ver hoja Supuestos
A11: Mesa de ayuda | B11: teléfono/WhatsApp de soporte | C11: horario extendido; guardia para incidentes críticos | D11: dentro de soporte
A12: Seguridad | B12: usuarios, roles, auditoría, cifrado | C12: revisión de seguridad externa 1 vez al año | D12: US$ 3.000–8.000/año
A13: Legal | B13: autorización del Ministerio/SEDES, protección de datos, registro de software | C13: SENAPI (derecho de autor), convenio con el Ministerio | D13: US$ 500–2.000
A14: Internet en los centros | B14: conexión mínima | C14: funciona sin internet y sincroniza; 4G de respaldo | D14: lo cubre el Estado o el municipio
