Workbook

Sheet Fases
A1: SIVEC — Quanto entra, quanto custa e quanto sobra, por fase
A2: Preços: Supostos. Estabelecimentos: Departamentos e Municípios. Equipe e ferramentas: suas abas.
A4: Linha | B4: Fase 1 · Red Centro | C4: Fase 2 · Município Santa Cruz | D4: Fase 3 · Departamento Santa Cruz | E4: Fase 4 · Bolívia inteira
A5: Redes | B5: 1 | C5: ='Municípios'!D5 | D5: =Departamentos!C5 | E5: =Departamentos!C14
A6: Centros 1º nível | B6: 9 | C6: ='Municípios'!E5 | D6: =Departamentos!D5 | E6: =Departamentos!D14
A7: Hospitais 2º nível | B7: 1 | C7: ='Municípios'!F5 | D7: =Departamentos!E5 | E7: =Departamentos!E14
A8: 3º nível + labs + oncológico | B8: 1 | C8: ='Municípios'!G5 | D8: =Departamentos!F5 | E8: =Departamentos!F14
A9: Receita bruta mensal (US$) | B9: =B5*Supostos!$B$8+B6*Supostos!$B$5+B7*Supostos!$B$6+B8*Supostos!$B$7 | C9: =C5*Supostos!$B$8+C6*Supostos!$B$5+C7*Supostos!$B$6+C8*Supostos!$B$7 | D9: =D5*Supostos!$B$8+D6*Supostos!$B$5+D7*Supostos!$B$6+D8*Supostos!$B$7 | E9: =E5*Supostos!$B$8+E6*Supostos!$B$5+E7*Supostos!$B$6+E8*Supostos!$B$7
A10: Receita bruta anual (US$) | B10: =B9*12 | C10: =C9*12 | D10: =D9*12 | E10: =E9*12
A11: Receita bruta anual (Bs) | B11: =B10*Supostos!$B$9 | C11: =C10*Supostos!$B$9 | D11: =D10*Supostos!$B$9 | E11: =E10*Supostos!$B$9
A12: (−) Impostos sobre faturamento (US$/ano) | B12: =-B10*Supostos!$B$10 | C12: =-C10*Supostos!$B$10 | D12: =-D10*Supostos!$B$10 | E12: =-E10*Supostos!$B$10
A13: Receita líquida anual (US$) | B13: =B10+B12 | C13: =C10+C12 | D13: =D10+D12 | E13: =E10+E12
A14: (−) Equipe (US$/ano) | B14: =-Equipe!I22/Supostos!$B$9*12 | C14: =-Equipe!J22/Supostos!$B$9*12 | D14: =-Equipe!K22/Supostos!$B$9*12 | E14: =-Equipe!L22/Supostos!$B$9*12
A15: (−) Ferramentas e operação (US$/ano) | B15: =-Ferramentas!E22*12 | C15: =-Ferramentas!F22*12 | D15: =-Ferramentas!G22*12 | E15: =-Ferramentas!H22*12
A16: Resultado antes do IUE (US$/ano) | B16: =B13+B14+B15 | C16: =C13+C14+C15 | D16: =D13+D14+D15 | E16: =E13+E14+E15
A17: (−) IUE (US$/ano) | B17: =-MAX(0,B16)*Supostos!$B$11 | C17: =-MAX(0,C16)*Supostos!$B$11 | D17: =-MAX(0,D16)*Supostos!$B$11 | E17: =-MAX(0,E16)*Supostos!$B$11
A18: Lucro líquido anual (US$) | B18: =B16+B17 | C18: =C16+C17 | D18: =D16+D17 | E18: =E16+E17
A19: Lucro líquido anual (Bs) | B19: =B18*Supostos!$B$9 | C19: =C18*Supostos!$B$9 | D19: =D18*Supostos!$B$9 | E19: =E18*Supostos!$B$9
A20: Margem líquida (% da receita bruta) | B20: =IFERROR(B18/B10,0) | C20: =IFERROR(C18/C10,0) | D20: =IFERROR(D18/D10,0) | E20: =IFERROR(E18/E10,0)
A21: Pessoas na equipe | B21: =Equipe!E22 | C21: =Equipe!F22 | D21: =Equipe!G22 | E21: =Equipe!H22
A22: Estabelecimentos atendidos | B22: =B6+B7+B8 | C22: =C6+C7+C8 | D22: =D6+D7+D8 | E22: =E6+E7+E8
A24: Como ler:
A25: • Fase 1 = Red Centro (San Luis + 8 centros, 1 hospital 2º nível e o Oncológico).
A26: • Fase 2 = município de Santa Cruz de la Sierra (4 redes urbanas). Fase 3 = departamento de Santa Cruz (19 redes). Fase 4 = Bolívia inteira (106 redes).
A27: • A Fase 1 sozinha não paga uma equipe: o SIVEC fica de pé a partir da Fase 2. Até lá, o custo é basicamente o seu tempo.
A28: • Mude os preços na aba Supostos e as quantidades nas abas Departamentos e Municípios: tudo recalcula.

Sheet Supostos
A1: SIVEC — Supostos da métrica
A2: Células em azul = valores que você pode mudar. Amarelo = estimativa a confirmar. Todas as outras abas recalculam sozinhas.
A4: Suposto | B4: Valor | C4: Observação / fonte
A5: Preço mensal · centro de 1º nível (US$) | B5: 120 | C5: Definido pelo autor (26/09/2026).
A6: Preço mensal · hospital de 2º nível (US$) | B6: 275 | C6: Definido pelo autor (26/09/2026).
A7: Preço mensal · 3º nível, laboratório e oncológico (US$) | B7: 521 | C7: Definido pelo autor (26/09/2026).
A8: Preço mensal · rede de saúde (tablero do gestor + mapa) (US$) | B8: 250 | C8: PROPOSTA do Claude: o autor pediu para incluir a rede, mas não deu valor. Ajuste aqui.
A9: Câmbio (Bs por US$) | B9: 6.96 | C9: Tipo de câmbio oficial do Banco Central de Bolivia.
A10: Impostos sobre o faturamento (IVA 13% + IT 3%) | B10: 0.16 | C10: Bolívia: IVA 13% e IT 3% sobre a fatura. Supõe que o preço ao governo já inclui impostos.
A11: Imposto sobre o lucro (IUE) | B11: 0.25 | C11: Bolívia: IUE 25% sobre a utilidade.
A12: Encargos sociais sobre salário (patronais + aguinaldo + indenização) | B12: 0.33 | C12: Estimativa: aportes patronais ~16,7% + aguinaldo 8,3% + previsão de indenização 8,3%. Confirmar com o contador.
A15: Legenda
A16: Azul = entrada editável
A17: Fundo amarelo = estimativa (confirmar com SNIS/SEDES/município)
A18: Preto = fórmula
A19: Verde = vem de outra aba

Sheet Departamentos
A1: Receita potencial por departamento (100% dos estabelecimentos públicos)
A2: Redes: Ministério de Saúde (106 redes). Estabelecimentos: estimativa distribuída pela população e pelo nº de redes; Cochabamba com dado do SEDES.
A4: Departamento | B4: População (Censo 2024) | C4: Redes de saúde | D4: Centros 1º nível | E4: Hospitais 2º nível | F4: 3º nível + labs + oncológico | G4: Receita mensal (US$) | H4: Receita anual (US$) | I4: Receita mensal (Bs) | J4: Receita anual (Bs) | K4: Fonte / observação
A5: Santa Cruz | B5: 3122605 | C5: 19 | D5: 796 | E5: 52 | F5: 13 | G5: =C5*Supostos!$B$8+D5*Supostos!$B$5+E5*Supostos!$B$6+F5*Supostos!$B$7 | H5: =G5*12 | I5: =G5*Supostos!$B$9 | J5: =H5*Supostos!$B$9 | K5: Estimativa (1º e 2º distribuídos por população e redes).
A6: La Paz | B6: 3030917 | C6: 24 | D6: 864 | E6: 57 | F6: 13 | G6: =C6*Supostos!$B$8+D6*Supostos!$B$5+E6*Supostos!$B$6+F6*Supostos!$B$7 | H6: =G6*12 | I6: =G6*Supostos!$B$9 | J6: =H6*Supostos!$B$9 | K6: Estimativa (1º e 2º distribuídos por população e redes).
A7: Cochabamba | B7: 2005000 | C7: 16 | D7: 485 | E7: 56 | F7: 7 | G7: =C7*Supostos!$B$8+D7*Supostos!$B$5+E7*Supostos!$B$6+F7*Supostos!$B$7 | H7: =G7*12 | I7: =G7*Supostos!$B$9 | J7: =H7*Supostos!$B$9 | K7: SEDES Cochabamba: 264 centros + 221 postos (1º) e 41 básicos + 15 gerais (2º).
A8: Potosí | B8: 856000 | C8: 11 | D8: 314 | E8: 21 | F8: 3 | G8: =C8*Supostos!$B$8+D8*Supostos!$B$5+E8*Supostos!$B$6+F8*Supostos!$B$7 | H8: =G8*12 | I8: =G8*Supostos!$B$9 | J8: =H8*Supostos!$B$9 | K8: Estimativa (1º e 2º distribuídos por população e redes).
A9: Chuquisaca | B9: 600000 | C9: 7 | D9: 208 | E9: 14 | F9: 4 | G9: =C9*Supostos!$B$8+D9*Supostos!$B$5+E9*Supostos!$B$6+F9*Supostos!$B$7 | H9: =G9*12 | I9: =G9*Supostos!$B$9 | J9: =H9*Supostos!$B$9 | K9: Estimativa (1º e 2º distribuídos por população e redes).
A10: Oruro | B10: 570000 | C10: 6 | D10: 187 | E10: 12 | F10: 3 | G10: =C10*Supostos!$B$8+D10*Supostos!$B$5+E10*Supostos!$B$6+F10*Supostos!$B$7 | H10: =G10*12 | I10: =G10*Supostos!$B$9 | J10: =H10*Supostos!$B$9 | K10: Estimativa (1º e 2º distribuídos por população e redes).
A11: Tarija | B11: 535000 | C11: 11 | D11: 264 | E11: 17 | F11: 4 | G11: =C11*Supostos!$B$8+D11*Supostos!$B$5+E11*Supostos!$B$6+F11*Supostos!$B$7 | H11: =G11*12 | I11: =G11*Supostos!$B$9 | J11: =H11*Supostos!$B$9 | K11: Estimativa (1º e 2º distribuídos por população e redes).
A12: Beni | B12: 477000 | C12: 9 | D12: 222 | E12: 15 | F12: 2 | G12: =C12*Supostos!$B$8+D12*Supostos!$B$5+E12*Supostos!$B$6+F12*Supostos!$B$7 | H12: =G12*12 | I12: =G12*Supostos!$B$9 | J12: =H12*Supostos!$B$9 | K12: Estimativa (1º e 2º distribuídos por população e redes).
A13: Pando | B13: 131000 | C13: 3 | D13: 70 | E13: 5 | F13: 2 | G13: =C13*Supostos!$B$8+D13*Supostos!$B$5+E13*Supostos!$B$6+F13*Supostos!$B$7 | H13: =G13*12 | I13: =G13*Supostos!$B$9 | J13: =H13*Supostos!$B$9 | K13: Estimativa (1º e 2º distribuídos por população e redes).
A14: BOLÍVIA (total) | B14: =SUM(B5:B13) | C14: =SUM(C5:C13) | D14: =SUM(D5:D13) | E14: =SUM(E5:E13) | F14: =SUM(F5:F13) | G14: =SUM(G5:G13) | H14: =SUM(H5:H13) | I14: =SUM(I5:I13) | J14: =SUM(J5:J13)
A16: Notas:
A17: • 3º nível: 39 hospitais de 3º nível recebem recursos do SUS (Ministério de Saúde, abr/2025); somamos 1 laboratório de citologia por departamento e os institutos oncológicos de SC, LP e CB.
A18: • Totais nacionais usados na estimativa: ~3.500 estabelecimentos de 1º nível e ~230 de 2º nível no setor público (INE: 2.958 e 214 em 2008; 3.574 no total em 2012; 4.133 em 2020 contando todos os setores).
A19: • Confirmar com as listas oficiais do SNIS por departamento (minsalud.gob.bo/images/web/SUS/Estab_<Departamento>.pdf) e trocar as células amarelas.

Sheet Municípios
A1: Receita potencial por cidade (as 16 maiores)
A2: Estimativas por cidade. Onde há fonte, está indicada; o resto é estimativa para confirmar com cada município.
A4: Município | B4: Departamento | C4: População (aprox.) | D4: Redes | E4: Centros 1º nível | F4: Hospitais 2º nível | G4: 3º nível + labs | H4: Receita mensal (US$) | I4: Receita anual (US$) | J4: Receita mensal (Bs) | K4: Receita anual (Bs) | L4: Fonte / observação
A5: Santa Cruz de la Sierra | B5: Santa Cruz | C5: 1600000 | D5: 4 | E5: 65 | F5: 10 | G5: 8 | H5: =D5*Supostos!$B$8+E5*Supostos!$B$5+F5*Supostos!$B$6+G5*Supostos!$B$7 | I5: =H5*12 | J5: =H5*Supostos!$B$9 | K5: =I5*Supostos!$B$9 | L5: Redes Norte, Sur, Este e Centro e 65 centros (El Deber, 2020). 2º e 3º nível: estimativa.
A6: La Paz | B6: La Paz | C6: 760000 | D6: 4 | E6: 150 | F6: 29 | G6: 17 | H6: =D6*Supostos!$B$8+E6*Supostos!$B$5+F6*Supostos!$B$6+G6*Supostos!$B$7 | I6: =H6*12 | J6: =H6*Supostos!$B$9 | K6: =I6*Supostos!$B$9 | L6: GAM La Paz 2017: 150 de 1º, 29 de 2º, 17 de 3º nível (todos os setores). Redes: estimativa.
A7: El Alto | B7: La Paz | C7: 890000 | D7: 5 | E7: 90 | F7: 6 | G7: 2 | H7: =D7*Supostos!$B$8+E7*Supostos!$B$5+F7*Supostos!$B$6+G7*Supostos!$B$7 | I7: =H7*12 | J7: =H7*Supostos!$B$9 | K7: =I7*Supostos!$B$9 | L7: Estimativa.
A8: Cochabamba (Cercado) | B8: Cochabamba | C8: 670000 | D8: 4 | E8: 60 | F8: 6 | G8: 5 | H8: =D8*Supostos!$B$8+E8*Supostos!$B$5+F8*Supostos!$B$6+G8*Supostos!$B$7 | I8: =H8*12 | J8: =H8*Supostos!$B$9 | K8: =I8*Supostos!$B$9 | L8: Estimativa.
A9: Sucre | B9: Chuquisaca | C9: 300000 | D9: 2 | E9: 30 | F9: 3 | G9: 3 | H9: =D9*Supostos!$B$8+E9*Supostos!$B$5+F9*Supostos!$B$6+G9*Supostos!$B$7 | I9: =H9*12 | J9: =H9*Supostos!$B$9 | K9: =I9*Supostos!$B$9 | L9: Estimativa.
A10: Oruro | B10: Oruro | C10: 280000 | D10: 2 | E10: 30 | F10: 3 | G10: 2 | H10: =D10*Supostos!$B$8+E10*Supostos!$B$5+F10*Supostos!$B$6+G10*Supostos!$B$7 | I10: =H10*12 | J10: =H10*Supostos!$B$9 | K10: =I10*Supostos!$B$9 | L10: Estimativa.
A11: Tarija (Cercado) | B11: Tarija | C11: 270000 | D11: 2 | E11: 30 | F11: 3 | G11: 3 | H11: =D11*Supostos!$B$8+E11*Supostos!$B$5+F11*Supostos!$B$6+G11*Supostos!$B$7 | I11: =H11*12 | J11: =H11*Supostos!$B$9 | K11: =I11*Supostos!$B$9 | L11: Estimativa.
A12: Potosí | B12: Potosí | C12: 220000 | D12: 2 | E12: 25 | F12: 2 | G12: 2 | H12: =D12*Supostos!$B$8+E12*Supostos!$B$5+F12*Supostos!$B$6+G12*Supostos!$B$7 | I12: =H12*12 | J12: =H12*Supostos!$B$9 | K12: =I12*Supostos!$B$9 | L12: Estimativa.
A13: Sacaba | B13: Cochabamba | C13: 210000 | D13: 1 | E13: 20 | F13: 1 | G13: 0 | H13: =D13*Supostos!$B$8+E13*Supostos!$B$5+F13*Supostos!$B$6+G13*Supostos!$B$7 | I13: =H13*12 | J13: =H13*Supostos!$B$9 | K13: =I13*Supostos!$B$9 | L13: Estimativa.
A14: Quillacollo | B14: Cochabamba | C14: 150000 | D14: 1 | E14: 15 | F14: 1 | G14: 0 | H14: =D14*Supostos!$B$8+E14*Supostos!$B$5+F14*Supostos!$B$6+G14*Supostos!$B$7 | I14: =H14*12 | J14: =H14*Supostos!$B$9 | K14: =I14*Supostos!$B$9 | L14: Estimativa.
A15: Montero | B15: Santa Cruz | C15: 140000 | D15: 1 | E15: 15 | F15: 2 | G15: 0 | H15: =D15*Supostos!$B$8+E15*Supostos!$B$5+F15*Supostos!$B$6+G15*Supostos!$B$7 | I15: =H15*12 | J15: =H15*Supostos!$B$9 | K15: =I15*Supostos!$B$9 | L15: Estimativa.
A16: Trinidad | B16: Beni | C16: 130000 | D16: 1 | E16: 15 | F16: 1 | G16: 1 | H16: =D16*Supostos!$B$8+E16*Supostos!$B$5+F16*Supostos!$B$6+G16*Supostos!$B$7 | I16: =H16*12 | J16: =H16*Supostos!$B$9 | K16: =I16*Supostos!$B$9 | L16: Estimativa.
... A20: Cobija | B20: Pando | C20: 70000 | D20: 1 | E20: 8 | F20: 1 | G20: 1 | H20: =D20*Supostos!$B$8+E20*Supostos!$B$5+F20*Supostos!$B$6+G20*Supostos!$B$7 | I20: =H20*12 | J20: =H20*Supostos!$B$9 | K20: =I20*Supostos!$B$9 | L20: Estimativa.
A21: Total das 16 cidades | C21: =SUM(C5:C20) | D21: =SUM(D5:D20) | E21: =SUM(E5:E20) | F21: =SUM(F5:F20) | G21: =SUM(G5:G20) | H21: =SUM(H5:H20) | I21: =SUM(I5:I20) | J21: =SUM(J5:J20) | K21: =SUM(K5:K20)
A22: Participação das 16 cidades na receita da Bolívia | I22: =IFERROR(I21/Departamentos!H14,0)
A24: A Bolívia tem 339 municípios. As listas oficiais de estabelecimentos por município ficam no SNIS; os demais municípios estão contidos nos totais da aba Departamentos.

Sheet Equipe
A1: Equipe e cargos por fase
A2: Salário mensal bruto em Bs (estimativa de mercado boliviano). Encargos só para empregados; externos recebem honorário.
A4: Cargo | B4: O que faz | C4: Salário mensal (Bs) | D4: Externo? (1=sim) | E4: Pessoas · Fase 1 · Red Centro | F4: Pessoas · Fase 2 · Município Santa Cruz | G4: Pessoas · Fase 3 · Departamento Santa Cruz | H4: Pessoas · Fase 4 · Bolívia inteira | I4: Custo mensal · Fase 1 · Red Centro (Bs) | J4: Custo mensal · Fase 2 · Município Santa Cruz (Bs) | K4: Custo mensal · Fase 3 · Departamento Santa Cruz (Bs) | L4: Custo mensal · Fase 4 · Bolívia inteira (Bs)
A5: Fundador / diretor geral | B5: Você: visão, vendas grandes, relação com Ministério e SEDES, decisão clínica do produto. | C5: 12000 | D5: 0 | E5: 1 | F5: 1 | G5: 1 | H5: 1 | I5: =$C5*E5*(1+IF($D5=1,0,Supostos!$B$12)) | J5: =$C5*F5*(1+IF($D5=1,0,Supostos!$B$12)) | K5: =$C5*G5*(1+IF($D5=1,0,Supostos!$B$12)) | L5: =$C5*H5*(1+IF($D5=1,0,Supostos!$B$12))
A6: Líder técnico (CTO) | B6: Arquitetura, segurança, revisão de código, banco de dados e desempenho. | C6: 15000 | D6: 0 | E6: 0 | F6: 1 | G6: 1 | H6: 1 | I6: =$C6*E6*(1+IF($D6=1,0,Supostos!$B$12)) | J6: =$C6*F6*(1+IF($D6=1,0,Supostos!$B$12)) | K6: =$C6*G6*(1+IF($D6=1,0,Supostos!$B$12)) | L6: =$C6*H6*(1+IF($D6=1,0,Supostos!$B$12))
A7: Desenvolvedor full-stack pleno | B7: Programa módulos novos e correções. | C7: 9000 | D7: 0 | E7: 0 | F7: 1 | G7: 2 | H7: 4 | I7: =$C7*E7*(1+IF($D7=1,0,Supostos!$B$12)) | J7: =$C7*F7*(1+IF($D7=1,0,Supostos!$B$12)) | K7: =$C7*G7*(1+IF($D7=1,0,Supostos!$B$12)) | L7: =$C7*H7*(1+IF($D7=1,0,Supostos!$B$12))
A8: Desenvolvedor júnior | B8: Ajustes, relatórios, telas simples, testes. | C8: 5000 | D8: 0 | E8: 0 | F8: 0 | G8: 1 | H8: 2 | I8: =$C8*E8*(1+IF($D8=1,0,Supostos!$B$12)) | J8: =$C8*F8*(1+IF($D8=1,0,Supostos!$B$12)) | K8: =$C8*G8*(1+IF($D8=1,0,Supostos!$B$12)) | L8: =$C8*H8*(1+IF($D8=1,0,Supostos!$B$12))
A9: DevOps / segurança e proteção de dados | B9: Servidores, backups, monitoramento, cópias de segurança, auditoria de acesso. | C9: 12000 | D9: 0 | E9: 0 | F9: 0 | G9: 1 | H9: 2 | I9: =$C9*E9*(1+IF($D9=1,0,Supostos!$B$12)) | J9: =$C9*F9*(1+IF($D9=1,0,Supostos!$B$12)) | K9: =$C9*G9*(1+IF($D9=1,0,Supostos!$B$12)) | L9: =$C9*H9*(1+IF($D9=1,0,Supostos!$B$12))
A10: Analista de testes (QA) | B10: Testa cada versão antes de chegar aos centros. | C10: 6000 | D10: 0 | E10: 0 | F10: 0 | G10: 1 | H10: 2 | I10: =$C10*E10*(1+IF($D10=1,0,Supostos!$B$12)) | J10: =$C10*F10*(1+IF($D10=1,0,Supostos!$B$12)) | K10: =$C10*G10*(1+IF($D10=1,0,Supostos!$B$12)) | L10: =$C10*H10*(1+IF($D10=1,0,Supostos!$B$12))
A11: Suporte nível 1 (mesa de ajuda) | B11: Atende telefone e WhatsApp dos centros; ~1 pessoa a cada 300 estabelecimentos. | C11: 4000 | D11: 0 | E11: 0 | F11: 1 | G11: 3 | H11: 12 | I11: =$C11*E11*(1+IF($D11=1,0,Supostos!$B$12)) | J11: =$C11*F11*(1+IF($D11=1,0,Supostos!$B$12)) | K11: =$C11*G11*(1+IF($D11=1,0,Supostos!$B$12)) | L11: =$C11*H11*(1+IF($D11=1,0,Supostos!$B$12))
A12: Suporte nível 2 (técnico) | B12: Resolve o que o nível 1 não resolve; acesso ao banco. | C12: 6500 | D12: 0 | E12: 0 | F12: 0 | G12: 1 | H12: 4 | I12: =$C12*E12*(1+IF($D12=1,0,Supostos!$B$12)) | J12: =$C12*F12*(1+IF($D12=1,0,Supostos!$B$12)) | K12: =$C12*G12*(1+IF($D12=1,0,Supostos!$B$12)) | L12: =$C12*H12*(1+IF($D12=1,0,Supostos!$B$12))
A13: Implantador / capacitador (profissional de saúde) | B13: Vai aos centros, cadastra usuários, capacita o pessoal. | C13: 6000 | D13: 0 | E13: 1 | F13: 2 | G13: 4 | H13: 9 | I13: =$C13*E13*(1+IF($D13=1,0,Supostos!$B$12)) | J13: =$C13*F13*(1+IF($D13=1,0,Supostos!$B$12)) | K13: =$C13*G13*(1+IF($D13=1,0,Supostos!$B$12)) | L13: =$C13*H13*(1+IF($D13=1,0,Supostos!$B$12))
A14: Coordenador regional | B14: Responde por uma região (vários departamentos): implantação, SEDES e redes. | C14: 9000 | D14: 0 | E14: 0 | F14: 0 | G14: 0 | H14: 3 | I14: =$C14*E14*(1+IF($D14=1,0,Supostos!$B$12)) | J14: =$C14*F14*(1+IF($D14=1,0,Supostos!$B$12)) | K14: =$C14*G14*(1+IF($D14=1,0,Supostos!$B$12)) | L14: =$C14*H14*(1+IF($D14=1,0,Supostos!$B$12))
A15: Médico(a) referente clínico | B15: Valida fluxos clínicos, formulários oficiais e normas do Ministério. | C15: 10000 | D15: 0 | E15: 0 | F15: 0 | G15: 1 | H15: 1 | I15: =$C15*E15*(1+IF($D15=1,0,Supostos!$B$12)) | J15: =$C15*F15*(1+IF($D15=1,0,Supostos!$B$12)) | K15: =$C15*G15*(1+IF($D15=1,0,Supostos!$B$12)) | L15: =$C15*H15*(1+IF($D15=1,0,Supostos!$B$12))
A16: Gerente comercial e relações com governo | B16: Licitações, SICOES, propostas, contratos com municípios e governações. | C16: 10000 | D16: 0 | E16: 0 | F16: 0 | G16: 1 | H16: 1 | I16: =$C16*E16*(1+IF($D16=1,0,Supostos!$B$12)) | J16: =$C16*F16*(1+IF($D16=1,0,Supostos!$B$12)) | K16: =$C16*G16*(1+IF($D16=1,0,Supostos!$B$12)) | L16: =$C16*H16*(1+IF($D16=1,0,Supostos!$B$12))
... A21: Advogado (externo) | B21: Contratos, SENAPI, proteção de dados, licitações. | C21: 3000 | D21: 1 | E21: 0 | F21: 1 | G21: 1 | H21: 1 | I21: =$C21*E21*(1+IF($D21=1,0,Supostos!$B$12)) | J21: =$C21*F21*(1+IF($D21=1,0,Supostos!$B$12)) | K21: =$C21*G21*(1+IF($D21=1,0,Supostos!$B$12)) | L21: =$C21*H21*(1+IF($D21=1,0,Supostos!$B$12))
A22: TOTAL | E22: =SUM(E5:E21) | F22: =SUM(F5:F21) | G22: =SUM(G5:G21) | H22: =SUM(H5:H21) | I22: =SUM(I5:I21) | J22: =SUM(J5:J21) | K22: =SUM(K5:K21) | L22: =SUM(L5:L21)
A23: Custo mensal da equipe (US$) | I23: =I22/Supostos!$B$9 | J23: =J22/Supostos!$B$9 | K23: =K22/Supostos!$B$9 | L23: =L22/Supostos!$B$9
A25: Salários: estimativas do mercado boliviano de TI e saúde (Computrabajo, Glassdoor, Paylab); ajustar às ofertas reais. Encargos na aba Supostos.

Sheet Ferramentas
A1: Ferramentas e custos para manter o SIVEC funcionando
A2: Custo mensal em US$ por fase. Linhas "por pessoa" usam o total de pessoas da aba Equipe.
A4: Ferramenta | B4: Para que serve | C4: Fornecedor sugerido | D4: Tipo | E4: US$/mês · Fase 1 · Red Centro | F4: US$/mês · Fase 2 · Município Santa Cruz | G4: US$/mês · Fase 3 · Departamento Santa Cruz | H4: US$/mês · Fase 4 · Bolívia inteira
A5: Banco de dados, login e backups | B5: Onde ficam todos os dados; login de cada usuário; cópias diárias. | C5: Supabase (Pro → Team) + computação dedicada | D5: fixo | E5: 40 | F5: 135 | G5: 809 | H5: 2519
A6: Hospedagem do aplicativo | B6: Publica o sistema na internet com endereço próprio (sem arquivo HTML). | C6: Vercel / Cloudflare Pages | D6: fixo | E6: 0 | F6: 20 | G6: 20 | H6: 40
A7: Domínio e certificado | B7: sivec.bo / sivec.com.bo com HTTPS. | C7: NIC Bolivia + Cloudflare | D7: fixo | E7: 3 | F7: 3 | G7: 3 | H7: 3
A8: E-mail transacional | B8: Senhas, avisos e relatórios por e-mail. | C8: Resend / SendGrid | D8: fixo | E8: 0 | F8: 20 | G8: 50 | H8: 200
A9: WhatsApp Business API | B9: Avisos às pacientes: resultado pronto, controle, cita. | C9: Meta via 360dialog / Twilio | D9: fixo | E9: 30 | F9: 150 | G9: 500 | H9: 3000
A10: Monitoramento de erros | B10: Avisa a equipe quando algo falha num centro. | C10: Sentry | D10: fixo | E10: 0 | F10: 26 | G10: 80 | H10: 300
A11: Monitor de disponibilidade | B11: Alerta se o sistema cair, 24 h. | C11: Better Stack / UptimeRobot | D11: fixo | E11: 0 | F11: 25 | G11: 50 | H11: 100
A12: Backup externo | B12: Segunda cópia dos dados fora do Supabase. | C12: Backblaze B2 / AWS S3 | D12: fixo | E12: 5 | F12: 20 | G12: 50 | H12: 200
A13: Teste de segurança (pentest anual ÷ 12) | B13: Auditoria externa de segurança uma vez por ano. | C13: Empresa de segurança | D13: fixo | E13: 0 | F13: 300 | G13: 800 | H13: 2000
A14: Seguro de responsabilidade | B14: Cobre falhas e vazamentos de dados. | C14: Seguradora local | D14: fixo | E14: 0 | F14: 100 | G14: 200 | H14: 500
A15: Viagens de implantação | B15: Passagens e diárias para capacitar nos municípios. | C15: — | D15: fixo | E15: 0 | F15: 200 | G15: 1500 | H15: 5000
A16: Escritório e internet | B16: Espaço da equipe e conexão. | C16: — | D16: fixo | E16: 50 | F16: 300 | G16: 800 | H16: 3000
A17: E-mail e documentos da equipe | B17: Correio, Drive, calendário. | C17: Google Workspace | D17: por pessoa | E17: =7*Equipe!E22 | F17: =7*Equipe!F22 | G17: =7*Equipe!G22 | H17: =7*Equipe!H22
A18: Central de atendimento | B18: Tickets e chat de suporte aos centros. | C18: Freshdesk / Zendesk | D18: por pessoa | E18: =15*Equipe!E22 | F18: =15*Equipe!F22 | G18: =15*Equipe!G22 | H18: =15*Equipe!H22
A19: Código e versões | B19: Repositório, revisões, automação. | C19: GitHub Team | D19: por pessoa | E19: =4*Equipe!E22 | F19: =4*Equipe!F22 | G19: =4*Equipe!G22 | H19: =4*Equipe!H22
A20: Gerenciador de senhas | B20: Senhas da equipe com segurança. | C20: Bitwarden / 1Password | D20: por pessoa | E20: =4*Equipe!E22 | F20: =4*Equipe!F22 | G20: =4*Equipe!G22 | H20: =4*Equipe!H22
A21: Notebooks (amortizados em 36 meses) | B21: Equipamento da equipe. | C21: — | D21: por pessoa | E21: =28*Equipe!E22 | F21: =28*Equipe!F22 | G21: =28*Equipe!G22 | H21: =28*Equipe!H22
A22: TOTAL ferramentas (US$/mês) | E22: =SUM(E5:E21) | F22: =SUM(F5:F21) | G22: =SUM(G5:G21) | H22: =SUM(H5:H21)
A24: Fontes: preços públicos de Supabase (supabase.com/pricing, 2026), Sentry, GitHub, Google Workspace; itens marcados "Estimativa" nos comentários.
